Metadata-Version: 2.4
Name: iflow-mcp_canner_mcp-server
Version: 0.1.0
Summary: Add your description here
Requires-Python: >=3.11
Requires-Dist: httpx>=0.28.1
Requires-Dist: mcp[cli]>=1.19.0
Requires-Dist: orjson>=3.10.15
Requires-Dist: pydantic>=2.10.6
Requires-Dist: python-dotenv>=1.0.1
Requires-Dist: ruff>=0.11.0
